{"__html":"<h2 id=\"f0522bb2084005f58bfd9ed1e51bb5fc\">文件上传</h2>\n<h4 id=\"83a030ab564c83f5a18e09158078fb27\">接口说明</h4>\n<ul>\n<li>适用对象 : 管理中台</li>\n<li>请求类型 : POST</li>\n<li>请求路径 : /api/file/front/upload</li>\n</ul>\n<h4 id=\"2555926b9145afa000729eb25802cdf4\">请求头</h4>\n<table>\n<thead>\n<tr>\n<th align=\"left\">参数</th>\n<th align=\"center\">是否必填</th>\n<th align=\"left\">类型</th>\n<th align=\"left\">参数描述</th>\n<th align=\"left\">示例值</th>\n</tr>\n</thead>\n<tbody><tr>\n<td align=\"left\">X-Access-Token</td>\n<td align=\"center\">是</td>\n<td align=\"left\">String</td>\n<td align=\"left\">token</td>\n<td align=\"left\"></td>\n</tr>\n<tr>\n<td align=\"left\">etc-sys-id</td>\n<td align=\"center\">是</td>\n<td align=\"left\">String</td>\n<td align=\"left\">ETC系统标识</td>\n<td align=\"left\">管理中台:E01，电子签：E02，联盟中心：E03</td>\n</tr>\n</tbody></table>\n<h4 id=\"2cb0dec8bfec7f4c28ba6bf5198c1381\">请求参数</h4>\n<table>\n<thead>\n<tr>\n<th align=\"left\">参数</th>\n<th align=\"center\">是否必填</th>\n<th align=\"left\">类型</th>\n<th align=\"left\">最大长度</th>\n<th align=\"left\">参数描述</th>\n<th align=\"left\">示例值</th>\n</tr>\n</thead>\n<tbody><tr>\n<td align=\"left\">file</td>\n<td align=\"center\">是</td>\n<td align=\"left\">File</td>\n<td align=\"left\"></td>\n<td align=\"left\">文件</td>\n<td align=\"left\"></td>\n</tr>\n</tbody></table>\n<h4 id=\"3cde1cff5bb657779f9529472c404d60\">请求示例</h4>\n<pre><code></code></pre>\n<h4 id=\"275b6a35f969a8a08b2c141977778ef5\">应答报文</h4>\n<table>\n<thead>\n<tr>\n<th align=\"left\">参数</th>\n<th align=\"center\">是否必填</th>\n<th align=\"left\">类型</th>\n<th align=\"left\">最大长度</th>\n<th align=\"left\">参数描述</th>\n<th align=\"left\">示例值</th>\n</tr>\n</thead>\n<tbody><tr>\n<td align=\"left\">access_file_url</td>\n<td align=\"center\">String</td>\n<td align=\"left\">200</td>\n<td align=\"left\">文件访问地址</td>\n<td align=\"left\"></td>\n<td align=\"left\"></td>\n</tr>\n</tbody></table>\n<h4 id=\"9b03fe9ab6968117b906a0388e5e57f1\">应答样例</h4>\n<pre><code class=\"language-json\">{\n    &quot;requestId&quot;:&quot;eb053acf-66a0-4974-a7b4-2f2354460755&quot;,\n    &quot;code&quot;:&quot;000&quot;,\n    &quot;msg&quot;:&quot;成功&quot;,\n    &quot;data&quot;:{\n        &quot;access_file_url&quot;:&quot;http://test-etc-oss.ebaas.com/test1.png!style0.jpg&quot;\n    }\n}</code></pre>\n","key":"fdaf05cfa476a2d029b4220d4cf83f0a","fileName":"__inner-docs_ETC管理中台接口文档_基础服务_01-文件上传.json","mtimeMs":1622776519000,"birthtimeMs":1622776519000}